[
    {
        "node": {
            "title": "2113 - 2034",
            "Nid": "2433",
            "timestamp": "2025-04-01 01:08:38",
            "field_geo_point": "2034",
            "field_source": "2113",
            "field_period": "",
            "title_1": "Филиал \"Автобусный парк №3 г.Орши\" ОАО \"Витебскоблавтотранс\"",
            "title_2": "Филиал \"Автобусный парк №3 г.Орши\" ОАО \"Витебскоблавтотранс\"",
            "substances": [
                {
                    "field_name_of_substance": "Железо (II) оксид (в пересчете на железо)",
                    "field_name_of_substance_id": "77",
                    "field_code": "123",
                    "field_danger_class": "3",
                    "field_znachenie": "0.098",
                    "field_year_value": "0.181"
                },
                {
                    "field_name_of_substance": "Кадмий и его соединения (в пересчете на кадмий)",
                    "field_name_of_substance_id": "78",
                    "field_code": "124",
                    "field_danger_class": "1",
                    "field_znachenie": "2.0E-5",
                    "field_year_value": "1.2E-5"
                },
                {
                    "field_name_of_substance": "Марганец и его соединения в пересчете на марганец (IY) оксид",
                    "field_name_of_substance_id": "79",
                    "field_code": "143",
                    "field_danger_class": "2",
                    "field_znachenie": "0.004",
                    "field_year_value": "0.002"
                },
                {
                    "field_name_of_substance": "Натрий гидроксид (натр едкий",
                    "field_name_of_substance_id": "80",
                    "field_code": "150",
                    "field_danger_class": "0",
                    "field_znachenie": "0.001",
                    "field_year_value": "0.002"
                },
                {
                    "field_name_of_substance": "Ртуть и ее соединения (в пересчете на ртуть)",
                    "field_name_of_substance_id": "81",
                    "field_code": "183",
                    "field_danger_class": "1",
                    "field_znachenie": "4.0E-6",
                    "field_year_value": "2.0E-6"
                },
                {
                    "field_name_of_substance": "Свинец и его неорганические соединения (в пересчете на свинец)",
                    "field_name_of_substance_id": "82",
                    "field_code": "184",
                    "field_danger_class": "1",
                    "field_znachenie": "0.000124",
                    "field_year_value": "0.000128"
                },
                {
                    "field_name_of_substance": "Цинк и его соединения (в пересчете на цинк)",
                    "field_name_of_substance_id": "83",
                    "field_code": "229",
                    "field_danger_class": "3",
                    "field_znachenie": "0.002",
                    "field_year_value": "0.001"
                },
                {
                    "field_name_of_substance": "Азот (IV) оксид (азота диоксид)",
                    "field_name_of_substance_id": "84",
                    "field_code": "301",
                    "field_danger_class": "2",
                    "field_znachenie": "0.265",
                    "field_year_value": "3.624"
                },
                {
                    "field_name_of_substance": "Азот (IV) оксид (азота диоксид)",
                    "field_name_of_substance_id": "84",
                    "field_code": "304",
                    "field_danger_class": "3",
                    "field_znachenie": "0.001",
                    "field_year_value": "0.201"
                },
                {
                    "field_name_of_substance": "Сера диоксид (ангидрид сернистый",
                    "field_name_of_substance_id": "86",
                    "field_code": "330",
                    "field_danger_class": "3",
                    "field_znachenie": "0.017",
                    "field_year_value": "0.399"
                },
                {
                    "field_name_of_substance": "Углерод оксид (окись углерода, угарный газ)",
                    "field_name_of_substance_id": "201",
                    "field_code": "337",
                    "field_danger_class": "4",
                    "field_znachenie": "0.523",
                    "field_year_value": "7.585"
                },
                {
                    "field_name_of_substance": "Углеводороды предельные алифатического ряда С1-С10 (алканы)",
                    "field_name_of_substance_id": "88",
                    "field_code": "401",
                    "field_danger_class": "4",
                    "field_znachenie": "0.571",
                    "field_year_value": "0.084"
                },
                {
                    "field_name_of_substance": "Углеводороды непредельные (алкены)",
                    "field_name_of_substance_id": "89",
                    "field_code": "550",
                    "field_danger_class": "4",
                    "field_znachenie": "0.147",
                    "field_year_value": "0.069"
                },
                {
                    "field_name_of_substance": "Углеводороды алициклические (нафтены)",
                    "field_name_of_substance_id": "90",
                    "field_code": "551",
                    "field_danger_class": "4",
                    "field_znachenie": "0.378",
                    "field_year_value": "0.085"
                },
                {
                    "field_name_of_substance": "Ксилолы (смесь изомеров о-,м-,п-)",
                    "field_name_of_substance_id": "91",
                    "field_code": "616",
                    "field_danger_class": "3",
                    "field_znachenie": "0.189",
                    "field_year_value": "0.018"
                },
                {
                    "field_name_of_substance": "Углеводороды ароматические - производные бензола",
                    "field_name_of_substance_id": "92",
                    "field_code": "655",
                    "field_danger_class": "2",
                    "field_znachenie": "0.582",
                    "field_year_value": "0.114"
                },
                {
                    "field_name_of_substance": "Бенз(а)пирен",
                    "field_name_of_substance_id": "183",
                    "field_code": "703",
                    "field_danger_class": "1",
                    "field_znachenie": "1.0E-6",
                    "field_year_value": "9.0E-6"
                },
                {
                    "field_name_of_substance": "Твердые частицы (недифференцированная по составу пыль/аэрозоль)",
                    "field_name_of_substance_id": "10",
                    "field_code": "2902",
                    "field_danger_class": "3",
                    "field_znachenie": "2.097",
                    "field_year_value": "15.51"
                }
            ]
        }
    }
]